Workbook
Name выбранный_период: 'Планировщик проекта'!$J$2
Name ОбластьЗаголовка..BO60: 'Планировщик проекта'!$C$3:$C$4
Name ПериодПлан: 'Планировщик проекта'!A$4=MEDIAN('Планировщик проекта'!A$4,'Планировщик проекта'!#REF!,'Планировщик проекта'!#REF!+'Планировщик проекта'!#REF!-1)
Name ПериодФакт: 'Планировщик проекта'!A$4=MEDIAN('Планировщик проекта'!A$4,'Планировщик проекта'!$G1,'Планировщик проекта'!$G1+'Планировщик проекта'!$H1-1)
Name План: ПериодПлан*('Планировщик проекта'!#REF!>0)
Name ПроцентВыполнения: ПроцентВыполненияВнеплан*ПериодПлан
Name ФактВнеплан: ПериодФакт*('Планировщик проекта'!$G1>0)
Name ФактическиеЗначения: (ПериодФакт*('Планировщик проекта'!$G1>0))*ПериодПлан

Sheet Пример 1
A1: ИИ | D1: Проект «Обучение сотрудников кибербезопасности»
D2: ЭТАП 1. ПОДГОТОВКА (3 работы)
D3: 1. Разработка и утверждение устава проекта, проведение стартового совещания.
D4: 2. Анализ существующих регламентов информационной безопасности.
D5: 3. Проведение скрытой фишинг-атаки (замер «нулевого» уровня) и формирование отчета об уязвимостях.
D6: ЭТАП 2. НАСТРОЙКА ПЛАТФОРМЫ (3 работы)
D7: 4. Анализ рынка, выбор вендора и заключение договора с оплатой лицензии.
D8: 5. Создание учетных записей для 200 сотрудников.
D9: 6. Настройка интеграции с почтовым сервером (white-list IP-адресов).
D10: ЭТАП 3. РАЗРАБОТКА КОНТЕНТА И ОБУЧЕНИЕ (4 работы)
D11: 7. Подготовка курса по Закону РБ № 99-З «О персональных данных».
D12: 8. Разработка интерактивных модулей по фишингу, социальной инженерии, создание видеолекций и базы тестов.
D13: 9. Информирование сотрудников о старте программы.
... D17: 12. Анализ достижения KPI, подготовка отчета для директора и утверждение регламента регулярного обучения.
C22: № | D22: Содержание работы | E22: Предшествен- ники | F22: Длитель- ность (дни) | G22: Пояснение по длительности
C23: 1 | D23: Устав и стартовое совещание | E23: — | F23: 3 | G23: Утверждение устава + совещание с руководителями
C24: 2 | D24: Анализ регламентов ИБ | E24: 1 | F24: 5 | G24: Изучение внутренних документов по защите ПДн
C25: 3 | D25: Фишинг-замер + отчет | E25: 2 | F25: 4 | G25: Скрытая рассылка + обработка результатов
C26: 4 | D26: Выбор вендора + договор | E26: 1 | F26: 6 | G26: Анализ рынка, переговоры, подписание
C27: 5 | D27: Учетные записи (200 чел.) | E27: 4 | F27: 3 | G27: Импорт сотрудников в платформу
C28: 6 | D28: Настройка white-list | E28: 3, 4 | F28: 3 | G28: Внесение IP-адресов в безопасный список почты
C29: 7 | D29: Курс по ПДн (№ 99-З) | E29: 6 | F29: 8 | G29: Разработка юридического модуля обучения
C30: 8 | D30: Модули, видео, тесты | E30: 6 | F30: 10 | G30: Создание интерактивного контента по фишингу
C31: 9 | D31: Информирование сотрудников | E31: 7, 8 | F31: 2 | G31: Письмо от директора + инструкции
C32: 10 | D32: Микрообучение (4 недели) | E32: 9 | F32: 20 | G32: Основная фаза обучения (4 недели × 5 дней)
C33: 11 | D33: Итоговый фишинг + тест | E33: 10 | F33: 4 | G33: Контрольный замер + проверка знаний
C34: 12 | D34: Анализ KPI + отчет + регламент | E34: 11 | F34: 5 | G34: Подготовка дашборда и утверждение регламента

Sheet Пример 2
C3: Код WBS | D3: Название работы
C4: 1. | D4: Анализ и планирование
C5: 1.1. | D5: Анализ конкурентов и целевой аудитории
C6: 1.2. | D6: Составление и утверждение технического задания
C7: 1.3. | D7: Разработка финансовой модели и бюджета проекта
C8: 2. | D8: Проектирование
C9: 2.1. | D9: Проектирование дизайна и пользовательского интерфейса
C10: 2.2. | D10: Проектирование структуры базы данных и каталога товаров
C11: 2.3. | D11: Проектирование системы фильтров и поиска
C12: 3. | D12: Разработка
C13: 3.1. | D13: Разработка бэкенда на Python (модели, API, логика заказов)
C14: 3.2. | D14: Разработка фронтенда (каталог, корзина, личный кабинет)
... C27: 6.3. | D27: Развёртывание на сервере и открытие доступа пользователям
B31: Код | C31: Название работы | D31: Длительность (мес.) | E31: предшествующие работы
B32: 1.0 | C32: Анализ рынка, аудитории и утверждение ТЗ | D32: 2 | E32: —
B33: 2.0 | C33: Разработка финансовой модели и бюджета | D33: 1.5 | E33: 1.0
B34: 3.0 | C34: Проектирование дизайна и пользовательского интерфейса | D34: 2 | E34: 1.0
B35: 4.0 | C35: Проектирование архитектуры БД и структуры каталога | D35: 1.5 | E35: 1.0
B36: 5.0 | C36: Разработка бэкенда (API, логика, админ-панель) | D36: 4 | E36: 3.0, 4.0
B37: 6.0 | C37: Разработка фронтенда (каталог, корзина, ЛК) | D37: 4 | E37: 3.0, 5.0
B38: 7.0 | C38: Интеграция с платёжной системой и уведомлениями | D38: 2 | E38: 5.0
B39: 8.0 | C39: SEO-настройка и оптимизация | D39: 2 | E39: 6.0
B40: 9.0 | C40: Фотосъёмка и подготовка изображений товаров | D40: 5 | E40: 1.0
B41: 10.0 | C41: Наполнение каталога и статических страниц контентом | D41: 3 | E41: 6.0, 9.0
B42: 11.0 | C42: Комплексное тестирование (функции, безопасность, скорость) | D42: 2 | E42: 5.0, 6.0, 7.0, 10.0
B43: 12.0 | C43: Развёртывание на сервере и запуск для пользователей | D43: 1 | E43: 11.0

Sheet ТАБЛИЦА ДАННЫХ
B4: Столбец1 | C4: Столбец2 | D4: Столбец3 | E4: Столбец32 | F4: Столбец4 | G4: Столбец5 | H4: Столбец6 | I4: Столбец7 | J4: Столбец8 | K4: Столбец9 | L4: Столбец10
C5: ЗАДАЧА | D5: ПРЕДШЕСТВУЮЩИЕ РАБОТЫ | E5: ПОСЛЕДУЮЩИЕ РАБОТЫ | F5: РАННИЙ СТАРТ | G5: ДЛИТЕЛЬНОСТЬ | H5: РАННИЙ ФИНИШ | I5: ПОЗДНИЙ СТАРТ | J5: ПОЗДНИЙ ФИНИШ | K5: РЕЗЕРВ | L5: КРИТИЧЕСКИЙ ПУТЬ
F6: Ранний старт (ES) — самый ранний возможный день начала. ES = МАКС(EF всех предшественников) | G6: Длительность (D) — сколько времени занимает задача. | H6: Ранний финиш (EF) = ES + D — самый ранний возможный день окончания. | I6: LS = Позднее начало (Late Start) LS = LF - D | J6: (Late Finish) LF = МИН(LS всех последователей) | K6: Полный резерв (TF) =LS-ES, Насколько МОЖНО задержать ВСЮ задачу
B7: №
B8: 1 | C8: 1.0 Анализ и ТЗ | D8: — | E8: 2, 3, 4, 5 | F8: 1 | G8: 1 | H8: =F8+G8 -> 2 | I8: =J8-G8 -> 1 | J8: =MIN(I9,I10,I11,I12) -> 2 | K8: =I8-F8 -> 0 | L8: =IF(K8=0,"ДА","НЕТ") -> ДА
B9: 2 | C9: 2.0 Юр. документы | D9: 1 | E9: 9 | F9: =MAX(H8) -> 2 | G9: 1 | H9: =F9+G9 -> 3 | I9: =J9-G9 -> 5 | J9: =MIN(I16) -> 6 | K9: =I9-F9 -> 3 | L9: =IF(K9=0,"ДА","НЕТ") -> НЕТ
B10: 3 | C10: 3.0 Архитектура | D10: 1 | E10: 6, 7, 8 | F10: =MAX(H8) -> 2 | G10: 1 | H10: =F10+G10 -> 3 | I10: =J10-G10 -> 2 | J10: =MIN(I13,I14,I15) -> 3 | K10: =I10-F10 -> 0 | L10: =IF(K10=0,"ДА","НЕТ") -> ДА
B11: 4 | C11: 4.0 UX/UI-дизайн | D11: 1 | E11: 8 | F11: =MAX(H8) -> 2 | G11: 1 | H11: =F11+G11 -> 3 | I11: =J11-G11 -> 3 | J11: =MIN(I15) -> 4 | K11: =I11-F11 -> 1 | L11: =IF(K11=0,"ДА","НЕТ") -> НЕТ
B12: 5 | C12: 5.0 Eval-набор | D12: 1 | E12: 9 | F12: =MAX(H8) -> 2 | G12: 2 | H12: =F12+G12 -> 4 | I12: =J12-G12 -> 4 | J12: =MIN(I16) -> 6 | K12: =I12-F12 -> 2 | L12: =IF(K12=0,"ДА","НЕТ") -> НЕТ
B13: 6 | C13: 6.0 Ядро верификации | D13: 3 | E13: 9 | F13: =MAX(H10) -> 3 | G13: 3 | H13: =F13+G13 -> 6 | I13: =J13-G13 -> 3 | J13: =MIN(I16) -> 6 | K13: =I13-F13 -> 0 | L13: =IF(K13=0,"ДА","НЕТ") -> ДА
B14: 7 | C14: 7.0 Бэкенд | D14: 3 | E14: 9 | F14: =MAX(H10) -> 3 | G14: 2 | H14: =F14+G14 -> 5 | I14: =J14-G14 -> 4 | J14: =MIN(I16) -> 6 | K14: =I14-F14 -> 1 | L14: =IF(K14=0,"ДА","НЕТ") -> НЕТ
B15: 8 | C15: 8.0 Фронтенд | D15: 3, 4 | E15: 9 | F15: =MAX(H10,H11) -> 3 | G15: 2 | H15: =F15+G15 -> 5 | I15: =J15-G15 -> 4 | J15: =MIN(I16) -> 6 | K15: =I15-F15 -> 1 | L15: =IF(K15=0,"ДА","НЕТ") -> НЕТ
B16: 9 | C16: 9.0 Релиз MVP | D16: 2, 5, 6, 7, 8 | E16: 10, 11, 12 | F16: =MAX(H9,H12,H13,H14,H15) -> 6 | G16: 1 | H16: =F16+G16 -> 7 | I16: =J16-G16 -> 6 | J16: =MIN(I17,I18,I19) -> 7 | K16: =I16-F16 -> 0 | L16: =IF(K16=0,"ДА","НЕТ") -> ДА
B17: 10 | C17: 10.0 AI-слой | D17: 9 | E17: 13 | F17: =MAX(H16) -> 7 | G17: 2 | H17: =F17+G17 -> 9 | I17: =J17-G17 -> 8 | J17: =MIN(I20) -> 10 | K17: =I17-F17 -> 1 | L17: =IF(K17=0,"ДА","НЕТ") -> НЕТ
B18: 11 | C18: 11.0 Монетизация | D18: 9 | E18: 13 | F18: =MAX(H16) -> 7 | G18: 1 | H18: =F18+G18 -> 8 | I18: =J18-G18 -> 9 | J18: =MIN(I20) -> 10 | K18: =I18-F18 -> 2 | L18: =IF(K18=0,"ДА","НЕТ") -> НЕТ
B19: 12 | C19: 12.0 Надстройка Excel | D19: 9 | E19: 13 | F19: =MAX(H16) -> 7 | G19: 3 | H19: =F19+G19 -> 10 | I19: =J19-G19 -> 7 | J19: =MIN(I20) -> 10 | K19: =I19-F19 -> 0 | L19: =IF(K19=0,"ДА","НЕТ") -> ДА
B20: 13 | C20: 13.0 Бета v1 | D20: 10, 11, 12 | E20: 14 | F20: =MAX(H17,H18,H19) -> 10 | G20: 1 | H20: =F20+G20 -> 11 | I20: =J20-G20 -> 10 | J20: =MIN(I21) -> 11 | K20: =I20-F20 -> 0 | L20: =IF(K20=0,"ДА","НЕТ") -> ДА
B21: 14 | C21: 14.0 Тестирование v1 | D21: 13 | E21: 15 | F21: =MAX(H20) -> 11 | G21: 1 | H21: =F21+G21 -> 12 | I21: =J21-G21 -> 11 | J21: =MIN(I22) -> 12 | K21: =I21-F21 -> 0 | L21: =IF(K21=0,"ДА","НЕТ") -> ДА
B22: 15 | C22: 15.0 Запуск и закрытие | D22: 14 | E22: — | F22: =MAX(H21) -> 12 | G22: 1 | H22: =F22+G22 -> 13 | I22: =J22-G22 -> 12 | J22: =MAX(H8:H22) -> 13 | K22: =I22-F22 -> 0 | L22: =IF(K22=0,"ДА","НЕТ") -> ДА
B23: 16
B24: 17
B25: 18
B26: 19
B27: 20
B28: 21
C30: Проект TableMind. Единица времени — 1 месяц; период 1 = октябрь 2026 (старт 01.10.2026). Ранний старт считается от 1, поэтому EF и LF — номер месяца, следующего за окончанием. Длительность проекта — 12 мес., критический путь: 1.0 → 3.0 → 6.0 → 9.0 → 12.0 → 13.0 → 14.0 → 15.0.
C31: D, E — номера предшествующих и последующих работ (№ = порядковый номер работы в WBS: 1 → 1.0, 2 → 2.0 …). Длительности получены по PERT (O+4M+P)/6 с округлением до целого месяца — см. отчёт ПЗ4.
C33: Операция | D33: Описание | E33: Предшествующая операция | F33: Время операции
C34: А | D34: Утверждение приложения | E34: нет | F34: 5
C35: В | D35: Планы конструирования | E35: А | F35: 15
C36: С | D36: Изучение трафика | E36: А | F36: 10
C37: D | D37: Проверка наличия службы | E37: А | F37: 5
C38: Е | D38: Отчет персонала | E38: В, С | F38: 15
C39: F | D39: Одобрение комиссии | E39: В, C, D | F39: 10
C40: G | D40: Ожидание работ | E40: F | F40: 170
C41: Н | D41: Включение в работу | E41: Е, G | F41: 35

Sheet Планировщик проекта
C1: Планировщик проекта TableMind
C2: Выберите период для выделения справа. Условные обозначения, описывающие диаграммы. | I2: Рассматриваемый период: | J2: 6 | M2: Длительность (план.) | S2: Начало (факт.) | X2: % выполнения | AC2: Фактически (внепланово) | AK2: % выполнения (внепланово)
B3: № | C3: ДЕЙСТВИЕ | D3: ='ТАБЛИЦА ДАННЫХ'!D5 -> ПРЕДШЕСТВУЮЩИЕ РАБОТЫ | E3: ='ТАБЛИЦА ДАННЫХ'!E5 -> ПОСЛЕДУЮЩИЕ РАБОТЫ | F3: РЕЗЕРВ | G3: РАННЕЕ НАЧАЛО | H3: ДЛИТЕЛЬНОСТЬ | I3: КРИТИЧЕСКИЙ ПУТЬ | J3: ПЕРИОДЫ
J4: 1 | K4: 2 | L4: 3 | M4: 4 | N4: 5 | O4: 6 | P4: 7 | Q4: 8 | R4: 9 | S4: 10 | T4: 11 | U4: 12 | V4: 13 | W4: 14 | X4: 15 | Y4: 16 | Z4: 17 | AA4: 18 | AB4: 19 | AC4: 20 | AD4: 21 | AE4: 22 | AF4: 23 | AG4: 24 | AH4: 25 | AI4: 26 | AJ4: 27 | AK4: 28 | AL4: 29 | AM4: 30 | AN4: 31 | AO4: 32 | AP4: 33 | AQ4: 34 | AR4: 35 | AS4: 36 | AT4: 37 | AU4: 38 | AV4: 39 | AW4: 40 | AX4: 41 | AY4: 42 | AZ4: 43 | BA4: 44 | BB4: 45 | BC4: 46 | BD4: 47 | BE4: 48 | BF4: 49 | BG4: 50 | BH4: 51 | BI4: 52 | BJ4: 53 | BK4: 54 | BL4: 55 | BM4: 56 | BN4: 57 | BO4: 58 | BP4: 59 | BQ4: 60
B5: 1 | C5: ='ТАБЛИЦА ДАННЫХ'!C8 -> 1.0 Анализ и ТЗ | D5: ='ТАБЛИЦА ДАННЫХ'!D8 -> — | E5: ='ТАБЛИЦА ДАННЫХ'!E8 -> 2, 3, 4, 5 | F5: ='ТАБЛИЦА ДАННЫХ'!K8 -> 0 | G5: ='ТАБЛИЦА ДАННЫХ'!F8 -> 1 | H5: ='ТАБЛИЦА ДАННЫХ'!G8 -> 1 | I5: =IF('ТАБЛИЦА ДАННЫХ'!L8="ДА",100%,0) -> 1
B6: 2 | C6: ='ТАБЛИЦА ДАННЫХ'!C9 -> 2.0 Юр. документы | D6: ='ТАБЛИЦА ДАННЫХ'!D9 -> 1 | E6: ='ТАБЛИЦА ДАННЫХ'!E9 -> 9 | F6: ='ТАБЛИЦА ДАННЫХ'!K9 -> 3 | G6: ='ТАБЛИЦА ДАННЫХ'!F9 -> 2 | H6: ='ТАБЛИЦА ДАННЫХ'!G9 -> 1 | I6: =IF('ТАБЛИЦА ДАННЫХ'!L9="ДА",100%,0) -> 0
B7: 3 | C7: ='ТАБЛИЦА ДАННЫХ'!C10 -> 3.0 Архитектура | D7: ='ТАБЛИЦА ДАННЫХ'!D10 -> 1 | E7: ='ТАБЛИЦА ДАННЫХ'!E10 -> 6, 7, 8 | F7: ='ТАБЛИЦА ДАННЫХ'!K10 -> 0 | G7: ='ТАБЛИЦА ДАННЫХ'!F10 -> 2 | H7: ='ТАБЛИЦА ДАННЫХ'!G10 -> 1 | I7: =IF('ТАБЛИЦА ДАННЫХ'!L10="ДА",100%,0) -> 1
B8: 4 | C8: ='ТАБЛИЦА ДАННЫХ'!C11 -> 4.0 UX/UI-дизайн | D8: ='ТАБЛИЦА ДАННЫХ'!D11 -> 1 | E8: ='ТАБЛИЦА ДАННЫХ'!E11 -> 8 | F8: ='ТАБЛИЦА ДАННЫХ'!K11 -> 1 | G8: ='ТАБЛИЦА ДАННЫХ'!F11 -> 2 | H8: ='ТАБЛИЦА ДАННЫХ'!G11 -> 1 | I8: =IF('ТАБЛИЦА ДАННЫХ'!L11="ДА",100%,0) -> 0
B9: 5 | C9: ='ТАБЛИЦА ДАННЫХ'!C12 -> 5.0 Eval-набор | D9: ='ТАБЛИЦА ДАННЫХ'!D12 -> 1 | E9: ='ТАБЛИЦА ДАННЫХ'!E12 -> 9 | F9: ='ТАБЛИЦА ДАННЫХ'!K12 -> 2 | G9: ='ТАБЛИЦА ДАННЫХ'!F12 -> 2 | H9: ='ТАБЛИЦА ДАННЫХ'!G12 -> 2 | I9: =IF('ТАБЛИЦА ДАННЫХ'!L12="ДА",100%,0) -> 0
B10: 6 | C10: ='ТАБЛИЦА ДАННЫХ'!C13 -> 6.0 Ядро верификации | D10: ='ТАБЛИЦА ДАННЫХ'!D13 -> 3 | E10: ='ТАБЛИЦА ДАННЫХ'!E13 -> 9 | F10: ='ТАБЛИЦА ДАННЫХ'!K13 -> 0 | G10: ='ТАБЛИЦА ДАННЫХ'!F13 -> 3 | H10: ='ТАБЛИЦА ДАННЫХ'!G13 -> 3 | I10: =IF('ТАБЛИЦА ДАННЫХ'!L13="ДА",100%,0) -> 1
B11: 7 | C11: ='ТАБЛИЦА ДАННЫХ'!C14 -> 7.0 Бэкенд | D11: ='ТАБЛИЦА ДАННЫХ'!D14 -> 3 | E11: ='ТАБЛИЦА ДАННЫХ'!E14 -> 9 | F11: ='ТАБЛИЦА ДАННЫХ'!K14 -> 1 | G11: ='ТАБЛИЦА ДАННЫХ'!F14 -> 3 | H11: ='ТАБЛИЦА ДАННЫХ'!G14 -> 2 | I11: =IF('ТАБЛИЦА ДАННЫХ'!L14="ДА",100%,0) -> 0
B12: 8 | C12: ='ТАБЛИЦА ДАННЫХ'!C15 -> 8.0 Фронтенд | D12: ='ТАБЛИЦА ДАННЫХ'!D15 -> 3, 4 | E12: ='ТАБЛИЦА ДАННЫХ'!E15 -> 9 | F12: ='ТАБЛИЦА ДАННЫХ'!K15 -> 1 | G12: ='ТАБЛИЦА ДАННЫХ'!F15 -> 3 | H12: ='ТАБЛИЦА ДАННЫХ'!G15 -> 2 | I12: =IF('ТАБЛИЦА ДАННЫХ'!L15="ДА",100%,0) -> 0
B13: 9 | C13: ='ТАБЛИЦА ДАННЫХ'!C16 -> 9.0 Релиз MVP | D13: ='ТАБЛИЦА ДАННЫХ'!D16 -> 2, 5, 6, 7, 8 | E13: ='ТАБЛИЦА ДАННЫХ'!E16 -> 10, 11, 12 | F13: ='ТАБЛИЦА ДАННЫХ'!K16 -> 0 | G13: ='ТАБЛИЦА ДАННЫХ'!F16 -> 6 | H13: ='ТАБЛИЦА ДАННЫХ'!G16 -> 1 | I13: =IF('ТАБЛИЦА ДАННЫХ'!L16="ДА",100%,0) -> 1
B14: 10 | C14: ='ТАБЛИЦА ДАННЫХ'!C17 -> 10.0 AI-слой | D14: ='ТАБЛИЦА ДАННЫХ'!D17 -> 9 | E14: ='ТАБЛИЦА ДАННЫХ'!E17 -> 13 | F14: ='ТАБЛИЦА ДАННЫХ'!K17 -> 1 | G14: ='ТАБЛИЦА ДАННЫХ'!F17 -> 7 | H14: ='ТАБЛИЦА ДАННЫХ'!G17 -> 2 | I14: =IF('ТАБЛИЦА ДАННЫХ'!L17="ДА",100%,0) -> 0
B15: 11 | C15: ='ТАБЛИЦА ДАННЫХ'!C18 -> 11.0 Монетизация | D15: ='ТАБЛИЦА ДАННЫХ'!D18 -> 9 | E15: ='ТАБЛИЦА ДАННЫХ'!E18 -> 13 | F15: ='ТАБЛИЦА ДАННЫХ'!K18 -> 2 | G15: ='ТАБЛИЦА ДАННЫХ'!F18 -> 7 | H15: ='ТАБЛИЦА ДАННЫХ'!G18 -> 1 | I15: =IF('ТАБЛИЦА ДАННЫХ'!L18="ДА",100%,0) -> 0
B16: 12 | C16: ='ТАБЛИЦА ДАННЫХ'!C19 -> 12.0 Надстройка Excel | D16: ='ТАБЛИЦА ДАННЫХ'!D19 -> 9 | E16: ='ТАБЛИЦА ДАННЫХ'!E19 -> 13 | F16: ='ТАБЛИЦА ДАННЫХ'!K19 -> 0 | G16: ='ТАБЛИЦА ДАННЫХ'!F19 -> 7 | H16: ='ТАБЛИЦА ДАННЫХ'!G19 -> 3 | I16: =IF('ТАБЛИЦА ДАННЫХ'!L19="ДА",100%,0) -> 1
... B19: 15 | C19: ='ТАБЛИЦА ДАННЫХ'!C22 -> 15.0 Запуск и закрытие | D19: ='ТАБЛИЦА ДАННЫХ'!D22 -> 14 | E19: ='ТАБЛИЦА ДАННЫХ'!E22 -> — | F19: ='ТАБЛИЦА ДАННЫХ'!K22 -> 0 | G19: ='ТАБЛИЦА ДАННЫХ'!F22 -> 12 | H19: ='ТАБЛИЦА ДАННЫХ'!G22 -> 1 | I19: =IF('ТАБЛИЦА ДАННЫХ'!L22="ДА",100%,0) -> 1
